README
setup.py
django_grunt.egg-info/PKG-INFO
django_grunt.egg-info/SOURCES.txt
django_grunt.egg-info/dependency_links.txt
django_grunt.egg-info/requires.txt
django_grunt.egg-info/top_level.txt
grunt/__init__.py
grunt/conf.py
grunt/context_processors.py
grunt/tests.py
grunt/management/__init__.py
grunt/management/grunt.py
grunt/management/gruntserver.py
grunt/management/commands/__init__.py
grunt/management/commands/grunt.py
grunt/management/commands/gruntserver.py
grunt/views/__init__.py
grunt/views/mixins.py